langchain_zotero_retriever/__init__.py
langchain_zotero_retriever/retrievers.py
langchain_zotero_retriever-0.1.1.dist-info/METADATA
langchain_zotero_retriever-0.1.1.dist-info/WHEEL
langchain_zotero_retriever-0.1.1.dist-info/RECORD
